metrics4mdp/__init__.py
metrics4mdp/metrics.py
metrics4mdp/provider.py
metrics4mdp-0.1.2.dist-info/METADATA
metrics4mdp-0.1.2.dist-info/WHEEL
metrics4mdp-0.1.2.dist-info/top_level.txt
metrics4mdp-0.1.2.dist-info/RECORD
